aa_dependency_overrides/__init__.py
aa_dependency_overrides-0.7.1.dist-info/METADATA
aa_dependency_overrides-0.7.1.dist-info/WHEEL
aa_dependency_overrides-0.7.1.dist-info/licenses/LICENSE
aa_dependency_overrides-0.7.1.dist-info/RECORD
