Metadata-Version: 2.4
Name: aa-dependency-overrides
Version: 0.7.1
Summary: Dependency Overrides for Alliance Auth, in case one of the dependencies is causing issues after an update, due to a breaking change or bug.
Project-URL: Changelog, https://github.com/ppfeufer/aa-dependency-overrides/blob/master/CHANGELOG.md
Project-URL: Documentation, https://github.com/ppfeufer/aa-dependency-overrides/blob/master/README.md
Project-URL: Donation, https://ko-fi.com/ppfeufer
Project-URL: GitHub, https://github.com/ppfeufer/aa-dependency-overrides
Project-URL: Tracker, https://github.com/ppfeufer/aa-dependency-overrides/issues
Author-email: Peter Pfeufer <develop@ppfeufer.de>
License:                     GNU GENERAL PUBLIC LICENSE
License-File: LICENSE
Keywords: allianceauth,bug,dependency,fix,override,patch,workaround
Classifier: Environment :: Web Environment
Classifier: Intended Audience :: Developers
Classifier: License :: OSI Approved :: GNU General Public License v3 (GPLv3)
Classifier: Operating System :: OS Independent
Classifier: Programming Language :: Python
Classifier: Programming Language :: Python :: 3 :: Only
Classifier: Programming Language :: Python :: 3.10
Classifier: Programming Language :: Python :: 3.11
Classifier: Programming Language :: Python :: 3.12
Classifier: Programming Language :: Python :: 3.13
Classifier: Topic :: Internet :: WWW/HTTP
Classifier: Topic :: Internet :: WWW/HTTP :: Dynamic Content
Requires-Python: <3.14,>=3.10
Requires-Dist: allianceauth>=4.11
Requires-Dist: celery!=5.6.1
